odoo/addons/sale_by_packaging/README.rst
odoo/addons/sale_by_packaging/__init__.py
odoo/addons/sale_by_packaging/__manifest__.py
odoo/addons/sale_by_packaging/i18n/es.po
odoo/addons/sale_by_packaging/i18n/it.po
odoo/addons/sale_by_packaging/i18n/sale_by_packaging.pot
odoo/addons/sale_by_packaging/models/__init__.py
odoo/addons/sale_by_packaging/models/product_packaging.py
odoo/addons/sale_by_packaging/models/product_packaging_type.py
odoo/addons/sale_by_packaging/models/product_product.py
odoo/addons/sale_by_packaging/models/product_template.py
odoo/addons/sale_by_packaging/models/sale_order_line.py
odoo/addons/sale_by_packaging/readme/CONFIGURE.rst
odoo/addons/sale_by_packaging/readme/CONTRIBUTORS.rst
odoo/addons/sale_by_packaging/readme/DESCRIPTION.rst
odoo/addons/sale_by_packaging/readme/ROADMAP.rst
odoo/addons/sale_by_packaging/static/description/icon.png
odoo/addons/sale_by_packaging/static/description/index.html
odoo/addons/sale_by_packaging/tests/__init__.py
odoo/addons/sale_by_packaging/tests/common.py
odoo/addons/sale_by_packaging/tests/test_minimum_sellable_qty.py
odoo/addons/sale_by_packaging/tests/test_packaging_type_can_be_sold.py
odoo/addons/sale_by_packaging/tests/test_sale_line_onchanges.py
odoo/addons/sale_by_packaging/tests/test_sale_only_by_packaging.py
odoo/addons/sale_by_packaging/views/product_packaging.xml
odoo/addons/sale_by_packaging/views/product_packaging_type.xml
odoo/addons/sale_by_packaging/views/product_product.xml
odoo/addons/sale_by_packaging/views/product_template.xml
odoo/addons/sale_by_packaging/views/sale_order_line.xml
odoo14_addon_sale_by_packaging-14.0.2.1.1.dist-info/METADATA
odoo14_addon_sale_by_packaging-14.0.2.1.1.dist-info/WHEEL
odoo14_addon_sale_by_packaging-14.0.2.1.1.dist-info/top_level.txt
odoo14_addon_sale_by_packaging-14.0.2.1.1.dist-info/RECORD
